trochilidae/__init__.py
trochilidae/interoperable_filter.py
trochilidae/interoperable_get_arg_spec.py
trochilidae/interoperable_map.py
trochilidae/interoperable_reduce.py
trochilidae/tests/__init__.py
trochilidae/tests/test_interoperable_filter.py
trochilidae/tests/test_interoperable_get_arg_spec.py
trochilidae/tests/test_interoperable_map.py
trochilidae/tests/test_interoperable_reduce.py
trochilidae-2.2.0.0.dist-info/LICENSE
trochilidae-2.2.0.0.dist-info/METADATA
trochilidae-2.2.0.0.dist-info/WHEEL
trochilidae-2.2.0.0.dist-info/top_level.txt
trochilidae-2.2.0.0.dist-info/RECORD
